gbatchkit/__init__.py
gbatchkit/inputs.py
gbatchkit/jobs.py
gbatchkit/types.py
gbatchkit-1.0a5.dist-info/licenses/LICENSE
gbatchkit-1.0a5.dist-info/METADATA
gbatchkit-1.0a5.dist-info/WHEEL
gbatchkit-1.0a5.dist-info/top_level.txt
gbatchkit-1.0a5.dist-info/RECORD
