Metadata-Version: 2.4
Name: gbatchkit
Version: 1.0a5
Summary: Toolkit for running Google Cloud Batch jobs
Author-email: David Haley <dchaley@gmail.com>
License: Boost Software License - Version 1.0 - August 17th, 2003
Project-URL: Homepage, https://github.com/redwoodconsulting-io/gbatchkit-python
Keywords: batch,cloud,google,platform,gcp
Classifier: License :: OSI Approved :: Boost Software License 1.0 (BSL-1.0)
Classifier: Programming Language :: Python
Classifier: Programming Language :: Python :: 3
Classifier: Programming Language :: Python :: 3.9
Classifier: Programming Language :: Python :: 3.10
Classifier: Programming Language :: Python :: 3.11
Classifier: Programming Language :: Python :: 3.12
Classifier: Development Status :: 2 - Pre-Alpha
Requires-Python: <=3.12,>=3.9
License-File: LICENSE
Requires-Dist: pydantic
Requires-Dist: smart_open[gcs]
Provides-Extra: dev
Requires-Dist: black; extra == "dev"
Requires-Dist: build; extra == "dev"
Requires-Dist: bumpver; extra == "dev"
Requires-Dist: callee; extra == "dev"
Requires-Dist: isort; extra == "dev"
Requires-Dist: pip-tools; extra == "dev"
Requires-Dist: pytest; extra == "dev"
Requires-Dist: twine; extra == "dev"
Dynamic: license-file
